{
  "page_nb": 1,
  "type": "cours",
  "mecanique": "flashcard_audio_tap",
  "titre": {
    "fr": "La nuit et le jour",
    "ar": "اللَّيْلُ وَ النَّهَارُ"
  },
  "enonce": {
    "fr": "Tape sur chaque image pour entendre le mot en arabe",
    "ar": "اِضْرِبْ عَلَى كُلِّ صُورَةٍ لِتَسْمَعَ الكَلِمَةَ"
  },
  "elements": [
    {
      "id": "shams",
      "ar": "شَمْسٌ",
      "fr": "Soleil",
      "emoji": "☀️"
    },
    {
      "id": "nujum",
      "ar": "نُجُومٌ",
      "fr": "Étoiles",
      "emoji": "⭐"
    },
    {
      "id": "sahab",
      "ar": "سَحَابٌ",
      "fr": "Nuage",
      "emoji": "☁️"
    },
    {
      "id": "qamar",
      "ar": "قَمَرٌ",
      "fr": "Lune",
      "emoji": "🌕"
    },
    {
      "id": "qaws_quzah",
      "ar": "قَوْسُ قُزَحَ",
      "fr": "Arc-en-ciel",
      "emoji": "🌈"
    },
    {
      "id": "hilal",
      "ar": "هِلالٌ",
      "fr": "Croissant de lune",
      "emoji": "🌙"
    }
  ],
  "difficulte": 1,
  "duree_minutes": 5,
  "nom_pdf": "arabe_niveau2_04_1",
  "audio_assets": [
    {
      "id": "audio_p1_consigne",
      "texte_ar": "اِضْرِبْ عَلَى كُلِّ صُورَةٍ لِتَسْمَعَ الكَلِمَةَ",
      "voix_m": "arabe_niveau2_04_1_p1_consigne_m.mp3",
      "voix_f": "arabe_niveau2_04_1_p1_consigne_f.mp3",
      "statut": "a_generer"
    },
    {
      "id": "audio_shams",
      "texte_ar": "شَمْسٌ",
      "voix_m": "arabe_niveau2_04_1_p1_shams_m.mp3",
      "voix_f": "arabe_niveau2_04_1_p1_shams_f.mp3",
      "statut": "a_generer"
    },
    {
      "id": "audio_nujum",
      "texte_ar": "نُجُومٌ",
      "voix_m": "arabe_niveau2_04_1_p1_nujum_m.mp3",
      "voix_f": "arabe_niveau2_04_1_p1_nujum_f.mp3",
      "statut": "a_generer"
    },
    {
      "id": "audio_sahab",
      "texte_ar": "سَحَابٌ",
      "voix_m": "arabe_niveau2_04_1_p1_sahab_m.mp3",
      "voix_f": "arabe_niveau2_04_1_p1_sahab_f.mp3",
      "statut": "a_generer"
    },
    {
      "id": "audio_qamar",
      "texte_ar": "قَمَرٌ",
      "voix_m": "arabe_niveau2_04_1_p1_qamar_m.mp3",
      "voix_f": "arabe_niveau2_04_1_p1_qamar_f.mp3",
      "statut": "a_generer"
    },
    {
      "id": "audio_qaws_quzah",
      "texte_ar": "قَوْسُ قُزَحَ",
      "voix_m": "arabe_niveau2_04_1_p1_qaws_quzah_m.mp3",
      "voix_f": "arabe_niveau2_04_1_p1_qaws_quzah_f.mp3",
      "statut": "a_generer"
    },
    {
      "id": "audio_hilal",
      "texte_ar": "هِلالٌ",
      "voix_m": "arabe_niveau2_04_1_p1_hilal_m.mp3",
      "voix_f": "arabe_niveau2_04_1_p1_hilal_f.mp3",
      "statut": "a_generer"
    }
  ],
  "progression_xp": 10,
  "duree_estimee_minutes": 5,
  "_meta": {
    "schema_version": "2.0",
    "genere_le": "2026-04-15T08:41:27.810965",
    "niveau": 2,
    "lecon": 13,
    "nom_pdf": "arabe_niveau2_04_1",
    "bucket_audio": "audio-lessons/niveau2/lecon13/",
    "nb_audio_assets": 7
  }
}