{
  "page_nb": 10,
  "type": "exercice",
  "mecanique": "coloriage_selectif",
  "titre": {
    "fr": "Entoure la lettre dans les mots",
    "ar": "أَحِيطُ الحَرْفَ فِي الكَلِمَاتِ"
  },
  "enonce": {
    "fr": "Entoure la lettre cible (ك/ك ou ش/ش) chaque fois qu'elle apparaît dans les mots suivants.",
    "ar": "أَحِطْ بِالحَرْفِ الْمُحَدَّدِ (ك أو ش) فِي كُلِّ كَلِمَةٍ."
  },
  "elements": [
    {
      "id": "1",
      "ar": "فِكـر",
      "fr": "pensée",
      "emoji": "💭"
    },
    {
      "id": "2",
      "ar": "كَـان",
      "fr": "il était",
      "emoji": "⏳"
    },
    {
      "id": "3",
      "ar": "كـوخ",
      "fr": "cabane",
      "emoji": "🛖"
    },
    {
      "id": "4",
      "ar": "كَوْكَب",
      "fr": "planète",
      "emoji": "🪐"
    },
    {
      "id": "5",
      "ar": "إِكـرام",
      "fr": "générosité",
      "emoji": "🎁"
    },
    {
      "id": "6",
      "ar": "شَوْكَة",
      "fr": "fourchette",
      "emoji": "🍴"
    },
    {
      "id": "7",
      "ar": "مَاكِر",
      "fr": "rusé",
      "emoji": "🦊"
    },
    {
      "id": "8",
      "ar": "بَـرَك",
      "fr": "bénédiction",
      "emoji": "✨"
    },
    {
      "id": "9",
      "ar": "مَكَث",
      "fr": "il resta",
      "emoji": "🏠"
    },
    {
      "id": "10",
      "ar": "شَيْخ",
      "fr": "cheikh",
      "emoji": "👳"
    },
    {
      "id": "11",
      "ar": "شَوْكَة",
      "fr": "fourchette",
      "emoji": "🍴"
    },
    {
      "id": "12",
      "ar": "مِشْمِش",
      "fr": "abricot",
      "emoji": "🍑"
    },
    {
      "id": "13",
      "ar": "كَرَش",
      "fr": "ventre",
      "emoji": "🫃"
    },
    {
      "id": "14",
      "ar": "شَمْس",
      "fr": "soleil",
      "emoji": "☀️"
    },
    {
      "id": "15",
      "ar": "رِيشَة",
      "fr": "plume",
      "emoji": "🪶"
    },
    {
      "id": "16",
      "ar": "مَشَى",
      "fr": "il marcha",
      "emoji": "🚶"
    },
    {
      "id": "17",
      "ar": "رَشْوَة",
      "fr": "pot-de-vin",
      "emoji": "💰"
    },
    {
      "id": "18",
      "ar": "مَرَش",
      "fr": "égratignure",
      "emoji": "🩹"
    }
  ],
  "difficulte": 2,
  "duree_minutes": 8,
  "nom_pdf": "livre_3_5ans_tome2_a5_partie2",
  "audio_assets": [
    {
      "id": "audio_p10_consigne",
      "texte_ar": "أَحِطْ بِالحَرْفِ الْمُحَدَّدِ (ك أو ش) فِي كُلِّ كَلِمَةٍ.",
      "voix_m": "livre_3_5ans_tome2_a5_partie2_p10_consigne_m.mp3",
      "voix_f": "livre_3_5ans_tome2_a5_partie2_p10_consigne_f.mp3",
      "statut": "a_generer"
    },
    {
      "id": "audio_1",
      "texte_ar": "فِكـر",
      "voix_m": "livre_3_5ans_tome2_a5_partie2_p10_1_m.mp3",
      "voix_f": "livre_3_5ans_tome2_a5_partie2_p10_1_f.mp3",
      "statut": "a_generer"
    },
    {
      "id": "audio_2",
      "texte_ar": "كَـان",
      "voix_m": "livre_3_5ans_tome2_a5_partie2_p10_2_m.mp3",
      "voix_f": "livre_3_5ans_tome2_a5_partie2_p10_2_f.mp3",
      "statut": "a_generer"
    },
    {
      "id": "audio_3",
      "texte_ar": "كـوخ",
      "voix_m": "livre_3_5ans_tome2_a5_partie2_p10_3_m.mp3",
      "voix_f": "livre_3_5ans_tome2_a5_partie2_p10_3_f.mp3",
      "statut": "a_generer"
    },
    {
      "id": "audio_4",
      "texte_ar": "كَوْكَب",
      "voix_m": "livre_3_5ans_tome2_a5_partie2_p10_4_m.mp3",
      "voix_f": "livre_3_5ans_tome2_a5_partie2_p10_4_f.mp3",
      "statut": "a_generer"
    },
    {
      "id": "audio_5",
      "texte_ar": "إِكـرام",
      "voix_m": "livre_3_5ans_tome2_a5_partie2_p10_5_m.mp3",
      "voix_f": "livre_3_5ans_tome2_a5_partie2_p10_5_f.mp3",
      "statut": "a_generer"
    },
    {
      "id": "audio_6",
      "texte_ar": "شَوْكَة",
      "voix_m": "livre_3_5ans_tome2_a5_partie2_p10_6_m.mp3",
      "voix_f": "livre_3_5ans_tome2_a5_partie2_p10_6_f.mp3",
      "statut": "a_generer"
    },
    {
      "id": "audio_7",
      "texte_ar": "مَاكِر",
      "voix_m": "livre_3_5ans_tome2_a5_partie2_p10_7_m.mp3",
      "voix_f": "livre_3_5ans_tome2_a5_partie2_p10_7_f.mp3",
      "statut": "a_generer"
    },
    {
      "id": "audio_8",
      "texte_ar": "بَـرَك",
      "voix_m": "livre_3_5ans_tome2_a5_partie2_p10_8_m.mp3",
      "voix_f": "livre_3_5ans_tome2_a5_partie2_p10_8_f.mp3",
      "statut": "a_generer"
    },
    {
      "id": "audio_9",
      "texte_ar": "مَكَث",
      "voix_m": "livre_3_5ans_tome2_a5_partie2_p10_9_m.mp3",
      "voix_f": "livre_3_5ans_tome2_a5_partie2_p10_9_f.mp3",
      "statut": "a_generer"
    },
    {
      "id": "audio_10",
      "texte_ar": "شَيْخ",
      "voix_m": "livre_3_5ans_tome2_a5_partie2_p10_10_m.mp3",
      "voix_f": "livre_3_5ans_tome2_a5_partie2_p10_10_f.mp3",
      "statut": "a_generer"
    },
    {
      "id": "audio_11",
      "texte_ar": "شَوْكَة",
      "voix_m": "livre_3_5ans_tome2_a5_partie2_p10_11_m.mp3",
      "voix_f": "livre_3_5ans_tome2_a5_partie2_p10_11_f.mp3",
      "statut": "a_generer"
    },
    {
      "id": "audio_12",
      "texte_ar": "مِشْمِش",
      "voix_m": "livre_3_5ans_tome2_a5_partie2_p10_12_m.mp3",
      "voix_f": "livre_3_5ans_tome2_a5_partie2_p10_12_f.mp3",
      "statut": "a_generer"
    },
    {
      "id": "audio_13",
      "texte_ar": "كَرَش",
      "voix_m": "livre_3_5ans_tome2_a5_partie2_p10_13_m.mp3",
      "voix_f": "livre_3_5ans_tome2_a5_partie2_p10_13_f.mp3",
      "statut": "a_generer"
    },
    {
      "id": "audio_14",
      "texte_ar": "شَمْس",
      "voix_m": "livre_3_5ans_tome2_a5_partie2_p10_14_m.mp3",
      "voix_f": "livre_3_5ans_tome2_a5_partie2_p10_14_f.mp3",
      "statut": "a_generer"
    },
    {
      "id": "audio_15",
      "texte_ar": "رِيشَة",
      "voix_m": "livre_3_5ans_tome2_a5_partie2_p10_15_m.mp3",
      "voix_f": "livre_3_5ans_tome2_a5_partie2_p10_15_f.mp3",
      "statut": "a_generer"
    },
    {
      "id": "audio_16",
      "texte_ar": "مَشَى",
      "voix_m": "livre_3_5ans_tome2_a5_partie2_p10_16_m.mp3",
      "voix_f": "livre_3_5ans_tome2_a5_partie2_p10_16_f.mp3",
      "statut": "a_generer"
    },
    {
      "id": "audio_17",
      "texte_ar": "رَشْوَة",
      "voix_m": "livre_3_5ans_tome2_a5_partie2_p10_17_m.mp3",
      "voix_f": "livre_3_5ans_tome2_a5_partie2_p10_17_f.mp3",
      "statut": "a_generer"
    },
    {
      "id": "audio_18",
      "texte_ar": "مَرَش",
      "voix_m": "livre_3_5ans_tome2_a5_partie2_p10_18_m.mp3",
      "voix_f": "livre_3_5ans_tome2_a5_partie2_p10_18_f.mp3",
      "statut": "a_generer"
    }
  ],
  "progression_xp": 20,
  "duree_estimee_minutes": 5,
  "_meta": {
    "schema_version": "2.0",
    "genere_le": "2026-04-15T09:20:20.871063",
    "niveau": 1,
    "lecon": 25,
    "nom_pdf": "livre_3_5ans_tome2_a5_partie2",
    "bucket_audio": "audio-lessons/niveau1/lecon25/",
    "nb_audio_assets": 19
  }
}