{
  "page_nb": 49,
  "type": "exercice",
  "mecanique": "relier_mot_image",
  "titre": {
    "fr": "Je relie selon la position de la lettre خ dans le mot",
    "ar": "أَرْبِطُ بِمَا يُنَاسِبُ : أَسْمَعُ الْحَرْفَ فِي أَوَّلَ أَو وَسَطَ أَو آخِرِ الْكَلِمَةِ"
  },
  "enonce": {
    "fr": "Je relie selon que j'entends la lettre au début, au milieu ou à la fin du mot",
    "ar": "أَسْمَعُ الْكَلِمَةَ وَأَرْبِطُهَا بِمَكَانِ الْحَرْفِ خ فِي أَوَّلِ الْكَلِمَةِ أَوْ وَسَطِهَا أَوْ آخِرِهَا"
  },
  "elements": [
    {
      "id": "1",
      "ar": "أَخْطَبُوط",
      "fr": "pieuvre",
      "emoji": "🐙"
    },
    {
      "id": "2",
      "ar": "مُخَيَّم",
      "fr": "tente / camp",
      "emoji": "⛺"
    },
    {
      "id": "3",
      "ar": "خَرُوف",
      "fr": "mouton",
      "emoji": "🐑"
    },
    {
      "id": "4",
      "ar": "خَوْخ",
      "fr": "pêche / prune",
      "emoji": "🍑"
    },
    {
      "id": "5",
      "ar": "خَيْط",
      "fr": "pelote de laine",
      "emoji": "🧶"
    }
  ],
  "difficulte": 3,
  "duree_minutes": 5,
  "nom_pdf": "livre_arabe_niveau3",
  "audio_assets": [
    {
      "id": "audio_p49_consigne",
      "texte_ar": "أَسْمَعُ الْكَلِمَةَ وَأَرْبِطُهَا بِمَكَانِ الْحَرْفِ خ فِي أَوَّلِ الْكَلِمَةِ أَوْ وَسَطِهَا أَوْ آخِرِهَا",
      "voix_m": "livre_arabe_niveau3_p49_consigne_m.mp3",
      "voix_f": "livre_arabe_niveau3_p49_consigne_f.mp3",
      "statut": "a_generer"
    },
    {
      "id": "audio_1",
      "texte_ar": "أَخْطَبُوط",
      "voix_m": "livre_arabe_niveau3_p49_1_m.mp3",
      "voix_f": "livre_arabe_niveau3_p49_1_f.mp3",
      "statut": "a_generer"
    },
    {
      "id": "audio_2",
      "texte_ar": "مُخَيَّم",
      "voix_m": "livre_arabe_niveau3_p49_2_m.mp3",
      "voix_f": "livre_arabe_niveau3_p49_2_f.mp3",
      "statut": "a_generer"
    },
    {
      "id": "audio_3",
      "texte_ar": "خَرُوف",
      "voix_m": "livre_arabe_niveau3_p49_3_m.mp3",
      "voix_f": "livre_arabe_niveau3_p49_3_f.mp3",
      "statut": "a_generer"
    },
    {
      "id": "audio_4",
      "texte_ar": "خَوْخ",
      "voix_m": "livre_arabe_niveau3_p49_4_m.mp3",
      "voix_f": "livre_arabe_niveau3_p49_4_f.mp3",
      "statut": "a_generer"
    },
    {
      "id": "audio_5",
      "texte_ar": "خَيْط",
      "voix_m": "livre_arabe_niveau3_p49_5_m.mp3",
      "voix_f": "livre_arabe_niveau3_p49_5_f.mp3",
      "statut": "a_generer"
    }
  ],
  "progression_xp": 30,
  "duree_estimee_minutes": 5,
  "_meta": {
    "schema_version": "2.0",
    "genere_le": "2026-04-15T10:04:19.578870",
    "niveau": 3,
    "lecon": 46,
    "nom_pdf": "livre_arabe_niveau3",
    "bucket_audio": "audio-lessons/niveau3/lecon46/",
    "nb_audio_assets": 6
  }
}